<annotation>
	<folder>batch_146</folder>
	<filename>0912208899_1602086911_66.jpg</filename>
	<path>C:\Users\TLnet\Desktop\batch_146\0912208899_1602086911_66.jpg</path>
	<source>
		<database>Unknown</database>
	</source>
	<size>
		<width>960</width>
		<height>1280</height>
		<depth>3</depth>
	</size>
	<segmented>0</segmented>
	<object>
		<name>ac</name>
		<pose>Unspecified</pose>
		<truncated>0</truncated>
		<difficult>0</difficult>
		<bndbox>
			<xmin>757</xmin>
			<ymin>1091</ymin>
			<xmax>853</xmax>
			<ymax>1180</ymax>
		</bndbox>
	</object>
	<object>
		<name>mu</name>
		<pose>Unspecified</pose>
		<truncated>0</truncated>
		<difficult>0</difficult>
		<bndbox>
			<xmin>310</xmin>
			<ymin>175</ymin>
			<xmax>517</xmax>
			<ymax>287</ymax>
		</bndbox>
	</object>
</annotation>
