<annotation>
	<folder>batch_146</folder>
	<filename>0965351090_1602066553_47.jpg</filename>
	<path>C:\Users\TLnet\Desktop\batch_146\0965351090_1602066553_47.jpg</path>
	<source>
		<database>Unknown</database>
	</source>
	<size>
		<width>1458</width>
		<height>2592</height>
		<depth>3</depth>
	</size>
	<segmented>0</segmented>
	<object>
		<name>ad</name>
		<pose>Unspecified</pose>
		<truncated>0</truncated>
		<difficult>0</difficult>
		<bndbox>
			<xmin>395</xmin>
			<ymin>1761</ymin>
			<xmax>519</xmax>
			<ymax>1869</ymax>
		</bndbox>
	</object>
	<object>
		<name>bc</name>
		<pose>Unspecified</pose>
		<truncated>1</truncated>
		<difficult>0</difficult>
		<bndbox>
			<xmin>970</xmin>
			<ymin>1407</ymin>
			<xmax>1458</xmax>
			<ymax>1965</ymax>
		</bndbox>
	</object>
</annotation>
