<annotation>
	<folder>batch_92</folder>
	<filename>0967525179_1602091777_159.jpg</filename>
	<path>/home/tung/Desktop/roi_alll/test/batch_92/0967525179_1602091777_159.jpg</path>
	<source>
		<database>Unknown</database>
	</source>
	<size>
		<width>2592</width>
		<height>5184</height>
		<depth>3</depth>
	</size>
	<segmented>0</segmented>
	<object>
		<name>mu</name>
		<pose>Unspecified</pose>
		<truncated>0</truncated>
		<difficult>0</difficult>
		<bndbox>
			<xmin>1329</xmin>
			<ymin>3361</ymin>
			<xmax>2001</xmax>
			<ymax>4045</ymax>
		</bndbox>
	</object>
	<object>
		<name>ac</name>
		<pose>Unspecified</pose>
		<truncated>0</truncated>
		<difficult>0</difficult>
		<bndbox>
			<xmin>701</xmin>
			<ymin>3117</ymin>
			<xmax>873</xmax>
			<ymax>3367</ymax>
		</bndbox>
	</object>
</annotation>
