<annotation>
	<folder>batch_95</folder>
	<filename>0988635006_1602089396_11.jpg</filename>
	<path>/home/tung/Desktop/roi_alll/test/batch_95/0988635006_1602089396_11.jpg</path>
	<source>
		<database>Unknown</database>
	</source>
	<size>
		<width>2752</width>
		<height>5664</height>
		<depth>3</depth>
	</size>
	<segmented>0</segmented>
	<object>
		<name>ac</name>
		<pose>Unspecified</pose>
		<truncated>0</truncated>
		<difficult>0</difficult>
		<bndbox>
			<xmin>781</xmin>
			<ymin>4399</ymin>
			<xmax>1216</xmax>
			<ymax>4852</ymax>
		</bndbox>
	</object>
	<object>
		<name>bcq</name>
		<pose>Unspecified</pose>
		<truncated>1</truncated>
		<difficult>0</difficult>
		<bndbox>
			<xmin>2416</xmin>
			<ymin>3558</ymin>
			<xmax>2752</xmax>
			<ymax>4275</ymax>
		</bndbox>
	</object>
</annotation>
