<annotation>
	<folder>batch_167</folder>
	<filename>0869279101_1602090327_29.jpg</filename>
	<path>C:\Users\TLnet\Desktop\batch_167\0869279101_1602090327_29.jpg</path>
	<source>
		<database>Unknown</database>
	</source>
	<size>
		<width>3948</width>
		<height>5264</height>
		<depth>3</depth>
	</size>
	<segmented>0</segmented>
	<object>
		<name>bc</name>
		<pose>Unspecified</pose>
		<truncated>1</truncated>
		<difficult>0</difficult>
		<bndbox>
			<xmin>2457</xmin>
			<ymin>3607</ymin>
			<xmax>3948</xmax>
			<ymax>5259</ymax>
		</bndbox>
	</object>
	<object>
		<name>ac</name>
		<pose>Unspecified</pose>
		<truncated>0</truncated>
		<difficult>0</difficult>
		<bndbox>
			<xmin>522</xmin>
			<ymin>4207</ymin>
			<xmax>863</xmax>
			<ymax>4600</ymax>
		</bndbox>
	</object>
</annotation>
