<root>
<name>0948583663_1602058178_47.jpg</name>
<meta>
<positionX>0</positionX>
<positionY>0</positionY>
<positionZ>0</positionZ>
<positionT>0</positionT>
<pixelSizeX>1</pixelSizeX>
<pixelSizeY>1</pixelSizeY>
<pixelSizeZ>1</pixelSizeZ>
<timeInterval>1</timeInterval>
<channelName0>ch 0</channelName0>
<channelName1>ch 1</channelName1>
<channelName2>ch 2</channelName2>
</meta>
<rois>
<roi>
<classname>plugins.kernel.roi.roi2d.ROI2DPolygon</classname>
<id>216</id>
<name>bcq</name>
<selected>false</selected>
<readOnly>false</readOnly>
<properties/>
<color>-16711936</color>
<stroke>2</stroke>
<opacity>0.3</opacity>
<showName>false</showName>
<z>-1</z>
<t>-1</t>
<c>-1</c>
<points>
<point>
<pos_x>1201.3989036508583</pos_x>
<pos_y>2992.4056268776962</pos_y>
</point>
<point>
<pos_x>1091.650121393151</pos_x>
<pos_y>3060.122960611175</pos_y>
</point>
<point>
<pos_x>992.992971384893</pos_x>
<pos_y>3122.0025931607333</pos_y>
</point>
<point>
<pos_x>960.3018447549377</pos_x>
<pos_y>3151.1910990803362</pos_y>
</point>
<point>
<pos_x>958.5505343997615</pos_x>
<pos_y>3226.4974443529118</pos_y>
</point>
<point>
<pos_x>960.8856148733298</pos_x>
<pos_y>3247.513168615026</pos_y>
</point>
<point>
<pos_x>1009.3385346998707</pos_x>
<pos_y>3252.1833295621627</pos_y>
</point>
<point>
<pos_x>1172.2103977312552</pos_x>
<pos_y>3250.4320192069863</pos_y>
</point>
<point>
<pos_x>1269.1162373843372</pos_x>
<pos_y>3256.853490509299</pos_y>
</point>
<point>
<pos_x>1328.077019341935</pos_x>
<pos_y>3258.6048008644752</pos_y>
</point>
<point>
<pos_x>1382.3676403523966</pos_x>
<pos_y>3260.356111219651</pos_y>
</point>
<point>
<pos_x>1412.1399163903916</pos_x>
<pos_y>3242.8430076678897</pos_y>
</point>
<point>
<pos_x>1401.0482841409425</pos_x>
<pos_y>3179.7958348815473</pos_y>
</point>
</points>
</roi>
<roi>
<classname>plugins.kernel.roi.roi2d.ROI2DPolygon</classname>
<id>217</id>
<name>at</name>
<selected>false</selected>
<readOnly>false</readOnly>
<properties/>
<color>-16711936</color>
<stroke>2</stroke>
<opacity>0.3</opacity>
<showName>false</showName>
<z>-1</z>
<t>-1</t>
<c>-1</c>
<points>
<point>
<pos_x>1190.357238172095</pos_x>
<pos_y>1574.5531634182773</pos_y>
</point>
<point>
<pos_x>1125.0346433075147</pos_x>
<pos_y>1602.415881606961</pos_y>
</point>
<point>
<pos_x>1072.4050645066677</pos_x>
<pos_y>1625.3252276732119</pos_y>
</point>
<point>
<pos_x>1055.0682620781536</pos_x>
<pos_y>1653.1879458618955</pos_y>
</point>
<point>
<pos_x>1049.8053041980688</pos_x>
<pos_y>1686.932793445968</pos_y>
</point>
<point>
<pos_x>1111.1032842131729</pos_x>
<pos_y>1720.0584695147363</pos_y>
</point>
<point>
<pos_x>1190.047652414443</pos_x>
<pos_y>1754.1129028564606</pos_y>
</point>
<point>
<pos_x>1214.1953415113023</pos_x>
<pos_y>1762.4717183130658</pos_y>
</point>
<point>
<pos_x>1230.6033866668604</pos_x>
<pos_y>1754.7320743717648</pos_y>
</point>
<point>
<pos_x>1237.1046875775532</pos_x>
<pos_y>1707.6750392086547</pos_y>
</point>
<point>
<pos_x>1201.1927396899166</pos_x>
<pos_y>1581.0544643289702</pos_y>
</point>
</points>
</roi>
</rois>
<overlays/>
<lut>
<numChannel>3</numChannel>
<scaler0>
<cancross>false</cancross>
<integerdata>true</integerdata>
<absleftin>0</absleftin>
<absrightin>255</absrightin>
<leftin>0</leftin>
<rightin>255</rightin>
<leftout>0</leftout>
<rightout>255</rightout>
</scaler0>
<colormap0>
<name>Custom</name>
<enabled>true</enabled>
<type>RGB</type>
<red rawdata="false">
<point>
<index>0</index>
<value>0</value>
</point>
<point>
<index>255</index>
<value>255</value>
</point>
</red>
<green rawdata="false">
<point>
<index>0</index>
<value>0</value>
</point>
<point>
<index>255</index>
<value>0</value>
</point>
</green>
<blue rawdata="false">
<point>
<index>0</index>
<value>0</value>
</point>
<point>
<index>255</index>
<value>0</value>
</point>
</blue>
<gray rawdata="false">
<point>
<index>0</index>
<value>0</value>
</point>
<point>
<index>255</index>
<value>85</value>
</point>
</gray>
<alpha rawdata="false">
<point>
<index>0</index>
<value>255</value>
</point>
<point>
<index>255</index>
<value>255</value>
</point>
</alpha>
</colormap0>
<scaler1>
<cancross>false</cancross>
<integerdata>true</integerdata>
<absleftin>0</absleftin>
<absrightin>255</absrightin>
<leftin>0</leftin>
<rightin>255</rightin>
<leftout>0</leftout>
<rightout>255</rightout>
</scaler1>
<colormap1>
<name>Custom</name>
<enabled>true</enabled>
<type>RGB</type>
<red rawdata="false">
<point>
<index>0</index>
<value>0</value>
</point>
<point>
<index>255</index>
<value>0</value>
</point>
</red>
<green rawdata="false">
<point>
<index>0</index>
<value>0</value>
</point>
<point>
<index>255</index>
<value>255</value>
</point>
</green>
<blue rawdata="false">
<point>
<index>0</index>
<value>0</value>
</point>
<point>
<index>255</index>
<value>0</value>
</point>
</blue>
<gray rawdata="false">
<point>
<index>0</index>
<value>0</value>
</point>
<point>
<index>255</index>
<value>85</value>
</point>
</gray>
<alpha rawdata="false">
<point>
<index>0</index>
<value>255</value>
</point>
<point>
<index>255</index>
<value>255</value>
</point>
</alpha>
</colormap1>
<scaler2>
<cancross>false</cancross>
<integerdata>true</integerdata>
<absleftin>0</absleftin>
<absrightin>255</absrightin>
<leftin>0</leftin>
<rightin>255</rightin>
<leftout>0</leftout>
<rightout>255</rightout>
</scaler2>
<colormap2>
<name>Custom</name>
<enabled>true</enabled>
<type>RGB</type>
<red rawdata="false">
<point>
<index>0</index>
<value>0</value>
</point>
<point>
<index>255</index>
<value>0</value>
</point>
</red>
<green rawdata="false">
<point>
<index>0</index>
<value>0</value>
</point>
<point>
<index>255</index>
<value>0</value>
</point>
</green>
<blue rawdata="false">
<point>
<index>0</index>
<value>0</value>
</point>
<point>
<index>255</index>
<value>255</value>
</point>
</blue>
<gray rawdata="false">
<point>
<index>0</index>
<value>0</value>
</point>
<point>
<index>255</index>
<value>85</value>
</point>
</gray>
<alpha rawdata="false">
<point>
<index>0</index>
<value>255</value>
</point>
<point>
<index>255</index>
<value>255</value>
</point>
</alpha>
</colormap2>
</lut>
</root>
