<annotation>
	<folder>batch_91</folder>
	<filename>0332051368_1602084614_81.jpg</filename>
	<path>/home/tung/Desktop/roi_alll/test/batch_91/0332051368_1602084614_81.jpg</path>
	<source>
		<database>Unknown</database>
	</source>
	<size>
		<width>3024</width>
		<height>4032</height>
		<depth>3</depth>
	</size>
	<segmented>0</segmented>
	<object>
		<name>bc</name>
		<pose>Unspecified</pose>
		<truncated>0</truncated>
		<difficult>0</difficult>
		<bndbox>
			<xmin>1195</xmin>
			<ymin>3276</ymin>
			<xmax>1636</xmax>
			<ymax>3560</ymax>
		</bndbox>
	</object>
	<object>
		<name>ad</name>
		<pose>Unspecified</pose>
		<truncated>0</truncated>
		<difficult>0</difficult>
		<bndbox>
			<xmin>1690</xmin>
			<ymin>1930</ymin>
			<xmax>1795</xmax>
			<ymax>2055</ymax>
		</bndbox>
	</object>
</annotation>
