<annotation>
	<folder>batch_165</folder>
	<filename>0949153998_1602073014_3.jpg</filename>
	<path>/media/ailab-02/Data/Code/dataset/Pendding/batch_165/0949153998_1602073014_3.jpg</path>
	<source>
		<database>Unknown</database>
	</source>
	<size>
		<width>2472</width>
		<height>3296</height>
		<depth>3</depth>
	</size>
	<segmented>0</segmented>
	<object>
		<name>mu</name>
		<pose>Unspecified</pose>
		<truncated>0</truncated>
		<difficult>0</difficult>
		<bndbox>
			<xmin>1137</xmin>
			<ymin>9</ymin>
			<xmax>1804</xmax>
			<ymax>428</ymax>
		</bndbox>
	</object>
	<object>
		<name>ac</name>
		<pose>Unspecified</pose>
		<truncated>0</truncated>
		<difficult>0</difficult>
		<bndbox>
			<xmin>407</xmin>
			<ymin>2874</ymin>
			<xmax>646</xmax>
			<ymax>3132</ymax>
		</bndbox>
	</object>
</annotation>
