<root>
<name>0387983433_1602092537_7.jpg</name>
<meta>
<positionX>0</positionX>
<positionY>0</positionY>
<positionZ>0</positionZ>
<positionT>0</positionT>
<pixelSizeX>1</pixelSizeX>
<pixelSizeY>1</pixelSizeY>
<pixelSizeZ>1</pixelSizeZ>
<timeInterval>1</timeInterval>
<channelName0>ch 0</channelName0>
<channelName1>ch 1</channelName1>
<channelName2>ch 2</channelName2>
</meta>
<rois>
<roi>
<classname>plugins.kernel.roi.roi2d.ROI2DPolygon</classname>
<id>273</id>
<name>bcq</name>
<selected>false</selected>
<readOnly>false</readOnly>
<properties/>
<color>-16711936</color>
<stroke>2</stroke>
<opacity>0.3</opacity>
<showName>false</showName>
<z>-1</z>
<t>-1</t>
<c>-1</c>
<points>
<point>
<pos_x>3450.29103422561</pos_x>
<pos_y>3956.2121766285727</pos_y>
</point>
<point>
<pos_x>3226.044906241594</pos_x>
<pos_y>4194.1318490018575</pos_y>
</point>
<point>
<pos_x>3226.044906241594</pos_x>
<pos_y>4267.968988703912</pos_y>
</point>
<point>
<pos_x>3240.6300202568145</pos_x>
<pos_y>4359.12595129904</pos_y>
</point>
<point>
<pos_x>3333.6101221038457</pos_x>
<pos_y>4361.860660176894</pos_y>
</point>
<point>
<pos_x>3630.7818201639643</pos_x>
<pos_y>4313.5474700014765</pos_y>
</point>
<point>
<pos_x>3745.639593033826</pos_x>
<pos_y>4300.785495238159</pos_y>
</point>
<point>
<pos_x>3776.63296031617</pos_x>
<pos_y>4261.588001322253</pos_y>
</point>
<point>
<pos_x>3760.2247070490466</pos_x>
<pos_y>4139.437671444781</pos_y>
</point>
<point>
<pos_x>3507.719920660541</pos_x>
<pos_y>3960.7700247583293</pos_y>
</point>
</points>
</roi>
<roi>
<classname>plugins.kernel.roi.roi2d.ROI2DPolygon</classname>
<id>274</id>
<name>ad</name>
<selected>false</selected>
<readOnly>false</readOnly>
<properties/>
<color>-16711936</color>
<stroke>2</stroke>
<opacity>0.3</opacity>
<showName>false</showName>
<z>-1</z>
<t>-1</t>
<c>-1</c>
<points>
<point>
<pos_x>977.5056467009139</pos_x>
<pos_y>4123.983050244628</pos_y>
</point>
<point>
<pos_x>829.2716001339656</pos_x>
<pos_y>4344.9356856934755</pos_y>
</point>
<point>
<pos_x>836.2637721418405</pos_x>
<pos_y>4488.2752118549115</pos_y>
</point>
<point>
<pos_x>953.7322618741392</pos_x>
<pos_y>4486.177560252549</pos_y>
</point>
<point>
<pos_x>1092.8764848308501</pos_x>
<pos_y>4481.283039847037</pos_y>
</point>
<point>
<pos_x>1127.1381276694374</pos_x>
<pos_y>4470.095564634436</pos_y>
</point>
<point>
<pos_x>1147.4154264922745</pos_x>
<pos_y>4427.443315386399</pos_y>
</point>
<point>
<pos_x>1140.4232544843994</pos_x>
<pos_y>4330.252124476939</pos_y>
</point>
<point>
<pos_x>1005.4743347324136</pos_x>
<pos_y>4128.877570650141</pos_y>
</point>
</points>
</roi>
</rois>
<overlays/>
<lut>
<numChannel>3</numChannel>
<scaler0>
<cancross>false</cancross>
<integerdata>true</integerdata>
<absleftin>0</absleftin>
<absrightin>255</absrightin>
<leftin>0</leftin>
<rightin>255</rightin>
<leftout>0</leftout>
<rightout>255</rightout>
</scaler0>
<colormap0>
<name>Custom</name>
<enabled>true</enabled>
<type>RGB</type>
<red rawdata="false">
<point>
<index>0</index>
<value>0</value>
</point>
<point>
<index>255</index>
<value>255</value>
</point>
</red>
<green rawdata="false">
<point>
<index>0</index>
<value>0</value>
</point>
<point>
<index>255</index>
<value>0</value>
</point>
</green>
<blue rawdata="false">
<point>
<index>0</index>
<value>0</value>
</point>
<point>
<index>255</index>
<value>0</value>
</point>
</blue>
<gray rawdata="false">
<point>
<index>0</index>
<value>0</value>
</point>
<point>
<index>255</index>
<value>85</value>
</point>
</gray>
<alpha rawdata="false">
<point>
<index>0</index>
<value>255</value>
</point>
<point>
<index>255</index>
<value>255</value>
</point>
</alpha>
</colormap0>
<scaler1>
<cancross>false</cancross>
<integerdata>true</integerdata>
<absleftin>0</absleftin>
<absrightin>255</absrightin>
<leftin>0</leftin>
<rightin>255</rightin>
<leftout>0</leftout>
<rightout>255</rightout>
</scaler1>
<colormap1>
<name>Custom</name>
<enabled>true</enabled>
<type>RGB</type>
<red rawdata="false">
<point>
<index>0</index>
<value>0</value>
</point>
<point>
<index>255</index>
<value>0</value>
</point>
</red>
<green rawdata="false">
<point>
<index>0</index>
<value>0</value>
</point>
<point>
<index>255</index>
<value>255</value>
</point>
</green>
<blue rawdata="false">
<point>
<index>0</index>
<value>0</value>
</point>
<point>
<index>255</index>
<value>0</value>
</point>
</blue>
<gray rawdata="false">
<point>
<index>0</index>
<value>0</value>
</point>
<point>
<index>255</index>
<value>85</value>
</point>
</gray>
<alpha rawdata="false">
<point>
<index>0</index>
<value>255</value>
</point>
<point>
<index>255</index>
<value>255</value>
</point>
</alpha>
</colormap1>
<scaler2>
<cancross>false</cancross>
<integerdata>true</integerdata>
<absleftin>0</absleftin>
<absrightin>255</absrightin>
<leftin>0</leftin>
<rightin>255</rightin>
<leftout>0</leftout>
<rightout>255</rightout>
</scaler2>
<colormap2>
<name>Custom</name>
<enabled>true</enabled>
<type>RGB</type>
<red rawdata="false">
<point>
<index>0</index>
<value>0</value>
</point>
<point>
<index>255</index>
<value>0</value>
</point>
</red>
<green rawdata="false">
<point>
<index>0</index>
<value>0</value>
</point>
<point>
<index>255</index>
<value>0</value>
</point>
</green>
<blue rawdata="false">
<point>
<index>0</index>
<value>0</value>
</point>
<point>
<index>255</index>
<value>255</value>
</point>
</blue>
<gray rawdata="false">
<point>
<index>0</index>
<value>0</value>
</point>
<point>
<index>255</index>
<value>85</value>
</point>
</gray>
<alpha rawdata="false">
<point>
<index>0</index>
<value>255</value>
</point>
<point>
<index>255</index>
<value>255</value>
</point>
</alpha>
</colormap2>
</lut>
</root>
