<annotation>
	<folder>batch_144</folder>
	<filename>0392682402_1602095973_299.jpg</filename>
	<path>C:\Users\TLnet\Desktop\batch_144\0392682402_1602095973_299.jpg</path>
	<source>
		<database>Unknown</database>
	</source>
	<size>
		<width>2448</width>
		<height>3264</height>
		<depth>3</depth>
	</size>
	<segmented>0</segmented>
	<object>
		<name>ad</name>
		<pose>Unspecified</pose>
		<truncated>0</truncated>
		<difficult>0</difficult>
		<bndbox>
			<xmin>865</xmin>
			<ymin>2445</ymin>
			<xmax>1009</xmax>
			<ymax>2615</ymax>
		</bndbox>
	</object>
	<object>
		<name>mu</name>
		<pose>Unspecified</pose>
		<truncated>0</truncated>
		<difficult>0</difficult>
		<bndbox>
			<xmin>1049</xmin>
			<ymin>664</ymin>
			<xmax>1392</xmax>
			<ymax>914</ymax>
		</bndbox>
	</object>
</annotation>
