<root>
<name>0946736287_1602088521_247.jpg</name>
<meta>
<positionX>0</positionX>
<positionY>0</positionY>
<positionZ>0</positionZ>
<positionT>0</positionT>
<pixelSizeX>1</pixelSizeX>
<pixelSizeY>1</pixelSizeY>
<pixelSizeZ>1</pixelSizeZ>
<timeInterval>1</timeInterval>
<channelName0>ch 0</channelName0>
<channelName1>ch 1</channelName1>
<channelName2>ch 2</channelName2>
</meta>
<rois>
<roi>
<classname>plugins.kernel.roi.roi2d.ROI2DPolygon</classname>
<id>66</id>
<name>ad</name>
<selected>false</selected>
<readOnly>false</readOnly>
<properties/>
<color>-16711936</color>
<stroke>2</stroke>
<opacity>0.3</opacity>
<showName>false</showName>
<z>-1</z>
<t>-1</t>
<c>-1</c>
<points>
<point>
<pos_x>2433.716679830022</pos_x>
<pos_y>3795.198868878105</pos_y>
</point>
<point>
<pos_x>2333.713212057386</pos_x>
<pos_y>3848.5639480930986</pos_y>
</point>
<point>
<pos_x>2262.4102910894526</pos_x>
<pos_y>3873.6769265472135</pos_y>
</point>
<point>
<pos_x>2223.8439313206336</pos_x>
<pos_y>3898.341458957505</pos_y>
</point>
<point>
<pos_x>2192.9011542968133</pos_x>
<pos_y>3928.8357899375014</pos_y>
</point>
<point>
<pos_x>2217.5656867071048</pos_x>
<pos_y>3953.051876303969</pos_y>
</point>
<point>
<pos_x>2279.8996867985684</pos_x>
<pos_y>4000.5871569492583</pos_y>
</point>
<point>
<pos_x>2332.3678739259153</pos_x>
<pos_y>4008.2107396942574</pos_y>
</point>
<point>
<pos_x>2380.8000466588514</pos_x>
<pos_y>3999.2418188177876</pos_y>
</point>
<point>
<pos_x>2408.603701375907</pos_x>
<pos_y>3954.3972144354398</pos_y>
</point>
<point>
<pos_x>2429.6806654356105</pos_x>
<pos_y>3933.7686964195595</pos_y>
</point>
<point>
<pos_x>2449.8607374076673</pos_x>
<pos_y>3805.961573929868</pos_y>
</point>
</points>
</roi>
<roi>
<classname>plugins.kernel.roi.roi2d.ROI2DPolygon</classname>
<id>67</id>
<name>bcq</name>
<selected>false</selected>
<readOnly>false</readOnly>
<properties/>
<color>-16711936</color>
<stroke>2</stroke>
<opacity>0.3</opacity>
<showName>false</showName>
<z>-1</z>
<t>-1</t>
<c>-1</c>
<points>
<point>
<pos_x>446.1914386478547</pos_x>
<pos_y>4547.9271939287355</pos_y>
</point>
<point>
<pos_x>128.25123968019233</pos_x>
<pos_y>4667.730747162927</pos_y>
</point>
<point>
<pos_x>70.6533775483694</pos_x>
<pos_y>4795.98198684312</pos_y>
</point>
<point>
<pos_x>75.26120651891529</pos_x>
<pos_y>4833.612590102577</pos_y>
</point>
<point>
<pos_x>221.17579058619987</pos_x>
<pos_y>4907.33785363131</pos_y>
</point>
<point>
<pos_x>340.97934382039153</pos_x>
<pos_y>4971.847459218952</pos_y>
</point>
<point>
<pos_x>392.43343399148665</pos_x>
<pos_y>4984.135003140407</pos_y>
</point>
<point>
<pos_x>453.1031821036734</pos_x>
<pos_y>4925.769169513494</pos_y>
</point>
<point>
<pos_x>493.8056713434949</pos_x>
<pos_y>4837.452447578032</pos_y>
</point>
<point>
<pos_x>474.6063839662207</pos_x>
<pos_y>4559.4467663551</pos_y>
</point>
</points>
</roi>
</rois>
<overlays/>
<lut>
<numChannel>3</numChannel>
<scaler0>
<cancross>false</cancross>
<integerdata>true</integerdata>
<absleftin>0</absleftin>
<absrightin>255</absrightin>
<leftin>0</leftin>
<rightin>255</rightin>
<leftout>0</leftout>
<rightout>255</rightout>
</scaler0>
<colormap0>
<name>Custom</name>
<enabled>true</enabled>
<type>RGB</type>
<red rawdata="false">
<point>
<index>0</index>
<value>0</value>
</point>
<point>
<index>255</index>
<value>255</value>
</point>
</red>
<green rawdata="false">
<point>
<index>0</index>
<value>0</value>
</point>
<point>
<index>255</index>
<value>0</value>
</point>
</green>
<blue rawdata="false">
<point>
<index>0</index>
<value>0</value>
</point>
<point>
<index>255</index>
<value>0</value>
</point>
</blue>
<gray rawdata="false">
<point>
<index>0</index>
<value>0</value>
</point>
<point>
<index>255</index>
<value>85</value>
</point>
</gray>
<alpha rawdata="false">
<point>
<index>0</index>
<value>255</value>
</point>
<point>
<index>255</index>
<value>255</value>
</point>
</alpha>
</colormap0>
<scaler1>
<cancross>false</cancross>
<integerdata>true</integerdata>
<absleftin>0</absleftin>
<absrightin>255</absrightin>
<leftin>0</leftin>
<rightin>255</rightin>
<leftout>0</leftout>
<rightout>255</rightout>
</scaler1>
<colormap1>
<name>Custom</name>
<enabled>true</enabled>
<type>RGB</type>
<red rawdata="false">
<point>
<index>0</index>
<value>0</value>
</point>
<point>
<index>255</index>
<value>0</value>
</point>
</red>
<green rawdata="false">
<point>
<index>0</index>
<value>0</value>
</point>
<point>
<index>255</index>
<value>255</value>
</point>
</green>
<blue rawdata="false">
<point>
<index>0</index>
<value>0</value>
</point>
<point>
<index>255</index>
<value>0</value>
</point>
</blue>
<gray rawdata="false">
<point>
<index>0</index>
<value>0</value>
</point>
<point>
<index>255</index>
<value>85</value>
</point>
</gray>
<alpha rawdata="false">
<point>
<index>0</index>
<value>255</value>
</point>
<point>
<index>255</index>
<value>255</value>
</point>
</alpha>
</colormap1>
<scaler2>
<cancross>false</cancross>
<integerdata>true</integerdata>
<absleftin>0</absleftin>
<absrightin>255</absrightin>
<leftin>0</leftin>
<rightin>255</rightin>
<leftout>0</leftout>
<rightout>255</rightout>
</scaler2>
<colormap2>
<name>Custom</name>
<enabled>true</enabled>
<type>RGB</type>
<red rawdata="false">
<point>
<index>0</index>
<value>0</value>
</point>
<point>
<index>255</index>
<value>0</value>
</point>
</red>
<green rawdata="false">
<point>
<index>0</index>
<value>0</value>
</point>
<point>
<index>255</index>
<value>0</value>
</point>
</green>
<blue rawdata="false">
<point>
<index>0</index>
<value>0</value>
</point>
<point>
<index>255</index>
<value>255</value>
</point>
</blue>
<gray rawdata="false">
<point>
<index>0</index>
<value>0</value>
</point>
<point>
<index>255</index>
<value>85</value>
</point>
</gray>
<alpha rawdata="false">
<point>
<index>0</index>
<value>255</value>
</point>
<point>
<index>255</index>
<value>255</value>
</point>
</alpha>
</colormap2>
</lut>
</root>
