<annotation>
	<folder>batch_145</folder>
	<filename>0969358373_1602073228_12.jpg</filename>
	<path>C:\Users\TLnet\Desktop\batch_145\0969358373_1602073228_12.jpg</path>
	<source>
		<database>Unknown</database>
	</source>
	<size>
		<width>2448</width>
		<height>3264</height>
		<depth>3</depth>
	</size>
	<segmented>0</segmented>
	<object>
		<name>ac</name>
		<pose>Unspecified</pose>
		<truncated>0</truncated>
		<difficult>0</difficult>
		<bndbox>
			<xmin>421</xmin>
			<ymin>2259</ymin>
			<xmax>580</xmax>
			<ymax>2425</ymax>
		</bndbox>
	</object>
	<object>
		<name>bc</name>
		<pose>Unspecified</pose>
		<truncated>0</truncated>
		<difficult>0</difficult>
		<bndbox>
			<xmin>1528</xmin>
			<ymin>1982</ymin>
			<xmax>2436</xmax>
			<ymax>2537</ymax>
		</bndbox>
	</object>
</annotation>
