<annotation>
	<folder>batch_200</folder>
	<filename>0972046813_1602088945_164.jpg</filename>
	<path>C:\Users\TLnet\Desktop\batch_200\0972046813_1602088945_164.jpg</path>
	<source>
		<database>Unknown</database>
	</source>
	<size>
		<width>4224</width>
		<height>5632</height>
		<depth>3</depth>
	</size>
	<segmented>0</segmented>
	<object>
		<name>bc</name>
		<pose>Unspecified</pose>
		<truncated>1</truncated>
		<difficult>0</difficult>
		<bndbox>
			<xmin>2844</xmin>
			<ymin>4172</ymin>
			<xmax>4224</xmax>
			<ymax>5556</ymax>
		</bndbox>
	</object>
	<object>
		<name>ad</name>
		<pose>Unspecified</pose>
		<truncated>0</truncated>
		<difficult>0</difficult>
		<bndbox>
			<xmin>1519</xmin>
			<ymin>3370</ymin>
			<xmax>1853</xmax>
			<ymax>3742</ymax>
		</bndbox>
	</object>
</annotation>
