<annotation>
	<folder>batch_200</folder>
	<filename>0975102268_1602066602_73.jpg</filename>
	<path>C:\Users\TLnet\Desktop\batch_200\0975102268_1602066602_73.jpg</path>
	<source>
		<database>Unknown</database>
	</source>
	<size>
		<width>1980</width>
		<height>2640</height>
		<depth>3</depth>
	</size>
	<segmented>0</segmented>
	<object>
		<name>mu</name>
		<pose>Unspecified</pose>
		<truncated>0</truncated>
		<difficult>0</difficult>
		<bndbox>
			<xmin>804</xmin>
			<ymin>31</ymin>
			<xmax>1253</xmax>
			<ymax>293</ymax>
		</bndbox>
	</object>
	<object>
		<name>ac</name>
		<pose>Unspecified</pose>
		<truncated>1</truncated>
		<difficult>0</difficult>
		<bndbox>
			<xmin>314</xmin>
			<ymin>2416</ymin>
			<xmax>527</xmax>
			<ymax>2640</ymax>
		</bndbox>
	</object>
</annotation>
