<annotation>
	<folder>batch_163</folder>
	<filename>0342292469_1602063023_25.jpg</filename>
	<path>/media/ailab-02/Data/Code/dataset/Pendding/batch_163/0342292469_1602063023_25.jpg</path>
	<source>
		<database>Unknown</database>
	</source>
	<size>
		<width>4312</width>
		<height>5760</height>
		<depth>3</depth>
	</size>
	<segmented>0</segmented>
	<object>
		<name>at</name>
		<pose>Unspecified</pose>
		<truncated>0</truncated>
		<difficult>0</difficult>
		<bndbox>
			<xmin>608</xmin>
			<ymin>3865</ymin>
			<xmax>901</xmax>
			<ymax>4260</ymax>
		</bndbox>
	</object>
	<object>
		<name>bc</name>
		<pose>Unspecified</pose>
		<truncated>1</truncated>
		<difficult>0</difficult>
		<bndbox>
			<xmin>3357</xmin>
			<ymin>3967</ymin>
			<xmax>4312</xmax>
			<ymax>5756</ymax>
		</bndbox>
	</object>
</annotation>
