<annotation>
	<folder>batch_163</folder>
	<filename>0975590226_1602061788_112.jpg</filename>
	<path>/media/ailab-02/Data/Code/dataset/Pendding/batch_163/0975590226_1602061788_112.jpg</path>
	<source>
		<database>Unknown</database>
	</source>
	<size>
		<width>2316</width>
		<height>3088</height>
		<depth>3</depth>
	</size>
	<segmented>0</segmented>
	<object>
		<name>ad</name>
		<pose>Unspecified</pose>
		<truncated>0</truncated>
		<difficult>0</difficult>
		<bndbox>
			<xmin>1686</xmin>
			<ymin>1912</ymin>
			<xmax>1842</xmax>
			<ymax>2060</ymax>
		</bndbox>
	</object>
	<object>
		<name>bq</name>
		<pose>Unspecified</pose>
		<truncated>0</truncated>
		<difficult>0</difficult>
		<bndbox>
			<xmin>532</xmin>
			<ymin>2426</ymin>
			<xmax>892</xmax>
			<ymax>2709</ymax>
		</bndbox>
	</object>
</annotation>
