<annotation>
	<folder>batch_183</folder>
	<filename>0846183286_1602083728_8.jpg</filename>
	<path>/media/ailab-02/Data/Code/dataset/Pendding/batch_183/0846183286_1602083728_8.jpg</path>
	<source>
		<database>Unknown</database>
	</source>
	<size>
		<width>960</width>
		<height>1280</height>
		<depth>3</depth>
	</size>
	<segmented>0</segmented>
	<object>
		<name>at</name>
		<pose>Unspecified</pose>
		<truncated>0</truncated>
		<difficult>0</difficult>
		<bndbox>
			<xmin>702</xmin>
			<ymin>777</ymin>
			<xmax>793</xmax>
			<ymax>886</ymax>
		</bndbox>
	</object>
	<object>
		<name>bc</name>
		<pose>Unspecified</pose>
		<truncated>1</truncated>
		<difficult>0</difficult>
		<bndbox>
			<xmin>81</xmin>
			<ymin>1127</ymin>
			<xmax>207</xmax>
			<ymax>1280</ymax>
		</bndbox>
	</object>
</annotation>
