<root>
<name>0984769162_1602073496_98.jpg</name>
<meta>
<positionX>0</positionX>
<positionY>0</positionY>
<positionZ>0</positionZ>
<positionT>0</positionT>
<pixelSizeX>1</pixelSizeX>
<pixelSizeY>1</pixelSizeY>
<pixelSizeZ>1</pixelSizeZ>
<timeInterval>1</timeInterval>
<channelName0>ch 0</channelName0>
<channelName1>ch 1</channelName1>
<channelName2>ch 2</channelName2>
</meta>
<rois>
<roi>
<classname>plugins.kernel.roi.roi2d.ROI2DPolygon</classname>
<id>281</id>
<name>mu</name>
<selected>false</selected>
<readOnly>false</readOnly>
<properties/>
<color>-16711936</color>
<stroke>2</stroke>
<opacity>0.3</opacity>
<showName>false</showName>
<z>-1</z>
<t>-1</t>
<c>-1</c>
<points>
<point>
<pos_x>964.8196164690535</pos_x>
<pos_y>248.86764881894976</pos_y>
</point>
<point>
<pos_x>940.1158425054077</pos_x>
<pos_y>284.0934005819261</pos_y>
</point>
<point>
<pos_x>922.274227976108</pos_x>
<pos_y>329.8411301442331</pos_y>
</point>
<point>
<pos_x>909.9223409942852</pos_x>
<pos_y>380.6211099583938</pos_y>
</point>
<point>
<pos_x>906.2625226293005</pos_x>
<pos_y>392.97299694021666</pos_y>
</point>
<point>
<pos_x>1063.6347123236364</pos_x>
<pos_y>351.3425630385173</pos_y>
</point>
<point>
<pos_x>1243.880766799126</pos_x>
<pos_y>337.1607668742022</pos_y>
</point>
<point>
<pos_x>1318.9070432813091</pos_x>
<pos_y>338.5331987610714</pos_y>
</point>
<point>
<pos_x>1324.396770828786</pos_x>
<pos_y>269.4541271219879</pos_y>
</point>
<point>
<pos_x>1329.8864983762628</pos_x>
<pos_y>222.33396567281176</pos_y>
</point>
<point>
<pos_x>1341.7809080624627</pos_x>
<pos_y>186.19325931858927</pos_y>
</point>
<point>
<pos_x>1358.7075680005162</pos_x>
<pos_y>164.23434912868194</pos_y>
</point>
<point>
<pos_x>1298.7780422738942</pos_x>
<pos_y>158.7446215812051</pos_y>
</point>
<point>
<pos_x>1205.910151262411</pos_x>
<pos_y>162.40443994618965</pos_y>
</point>
<point>
<pos_x>1139.5759433970659</pos_x>
<pos_y>177.0437134061279</pos_y>
</point>
<point>
<pos_x>1050.8253480461904</pos_x>
<pos_y>204.9498284391351</pos_y>
</point>
</points>
</roi>
<roi>
<classname>plugins.kernel.roi.roi2d.ROI2DPolygon</classname>
<id>282</id>
<name>atr</name>
<selected>false</selected>
<readOnly>false</readOnly>
<properties/>
<color>-16711936</color>
<stroke>2</stroke>
<opacity>0.3</opacity>
<showName>false</showName>
<z>-1</z>
<t>-1</t>
<c>-1</c>
<points>
<point>
<pos_x>1251.3922886330326</pos_x>
<pos_y>2369.927341344915</pos_y>
</point>
<point>
<pos_x>1144.6457233553454</pos_x>
<pos_y>2422.53266308248</pos_y>
</point>
<point>
<pos_x>1092.4243820684192</pos_x>
<pos_y>2459.010805893201</pos_y>
</point>
<point>
<pos_x>1077.8331249441308</pos_x>
<pos_y>2477.0578870732415</pos_y>
</point>
<point>
<pos_x>1083.5928317037183</pos_x>
<pos_y>2501.248655463509</pos_y>
</point>
<point>
<pos_x>1183.0437684192616</pos_x>
<pos_y>2556.541840355548</pos_y>
</point>
<point>
<pos_x>1216.0660871742296</pos_x>
<pos_y>2569.981156127919</pos_y>
</point>
<point>
<pos_x>1248.7044254785585</pos_x>
<pos_y>2528.1272870082503</pos_y>
</point>
<point>
<pos_x>1261.375780349651</pos_x>
<pos_y>2506.240401321818</pos_y>
</point>
<point>
<pos_x>1264.0636435041251</pos_x>
<pos_y>2376.8389894564198</pos_y>
</point>
</points>
</roi>
</rois>
<overlays/>
<lut>
<numChannel>3</numChannel>
<scaler0>
<cancross>false</cancross>
<integerdata>true</integerdata>
<absleftin>0</absleftin>
<absrightin>255</absrightin>
<leftin>0</leftin>
<rightin>255</rightin>
<leftout>0</leftout>
<rightout>255</rightout>
</scaler0>
<colormap0>
<name>Custom</name>
<enabled>true</enabled>
<type>RGB</type>
<red rawdata="false">
<point>
<index>0</index>
<value>0</value>
</point>
<point>
<index>255</index>
<value>255</value>
</point>
</red>
<green rawdata="false">
<point>
<index>0</index>
<value>0</value>
</point>
<point>
<index>255</index>
<value>0</value>
</point>
</green>
<blue rawdata="false">
<point>
<index>0</index>
<value>0</value>
</point>
<point>
<index>255</index>
<value>0</value>
</point>
</blue>
<gray rawdata="false">
<point>
<index>0</index>
<value>0</value>
</point>
<point>
<index>255</index>
<value>85</value>
</point>
</gray>
<alpha rawdata="false">
<point>
<index>0</index>
<value>255</value>
</point>
<point>
<index>255</index>
<value>255</value>
</point>
</alpha>
</colormap0>
<scaler1>
<cancross>false</cancross>
<integerdata>true</integerdata>
<absleftin>0</absleftin>
<absrightin>255</absrightin>
<leftin>0</leftin>
<rightin>255</rightin>
<leftout>0</leftout>
<rightout>255</rightout>
</scaler1>
<colormap1>
<name>Custom</name>
<enabled>true</enabled>
<type>RGB</type>
<red rawdata="false">
<point>
<index>0</index>
<value>0</value>
</point>
<point>
<index>255</index>
<value>0</value>
</point>
</red>
<green rawdata="false">
<point>
<index>0</index>
<value>0</value>
</point>
<point>
<index>255</index>
<value>255</value>
</point>
</green>
<blue rawdata="false">
<point>
<index>0</index>
<value>0</value>
</point>
<point>
<index>255</index>
<value>0</value>
</point>
</blue>
<gray rawdata="false">
<point>
<index>0</index>
<value>0</value>
</point>
<point>
<index>255</index>
<value>85</value>
</point>
</gray>
<alpha rawdata="false">
<point>
<index>0</index>
<value>255</value>
</point>
<point>
<index>255</index>
<value>255</value>
</point>
</alpha>
</colormap1>
<scaler2>
<cancross>false</cancross>
<integerdata>true</integerdata>
<absleftin>0</absleftin>
<absrightin>255</absrightin>
<leftin>0</leftin>
<rightin>255</rightin>
<leftout>0</leftout>
<rightout>255</rightout>
</scaler2>
<colormap2>
<name>Custom</name>
<enabled>true</enabled>
<type>RGB</type>
<red rawdata="false">
<point>
<index>0</index>
<value>0</value>
</point>
<point>
<index>255</index>
<value>0</value>
</point>
</red>
<green rawdata="false">
<point>
<index>0</index>
<value>0</value>
</point>
<point>
<index>255</index>
<value>0</value>
</point>
</green>
<blue rawdata="false">
<point>
<index>0</index>
<value>0</value>
</point>
<point>
<index>255</index>
<value>255</value>
</point>
</blue>
<gray rawdata="false">
<point>
<index>0</index>
<value>0</value>
</point>
<point>
<index>255</index>
<value>85</value>
</point>
</gray>
<alpha rawdata="false">
<point>
<index>0</index>
<value>255</value>
</point>
<point>
<index>255</index>
<value>255</value>
</point>
</alpha>
</colormap2>
</lut>
</root>
